dominx-0.2.0.post17.dist-info/RECORD
dominx-0.2.0.post17.dist-info/WHEEL
dominx-0.2.0.post17.dist-info/top_level.txt
dominx-0.2.0.post17.dist-info/LICENSE.txt
dominx-0.2.0.post17.dist-info/METADATA
dominx/display.c
dominx/__init__.py
dominx/display.cpython-37m-darwin.so
