Metadata-Version: 2.1
Name: dominx
Version: 0.2.0.post17
Summary: The Python library for game development.
Home-page: https://dominx.readthedocs.io/en/latest
Download-URL: https://pypi.org/project/dominx
Author-email: Zenthm <zenthm.dev@gmail.com>
License: MIT License
Project-URL: Documentation, https://dominx.readthedocs.io/en/latest
Project-URL: Source, https://github.com/zenthm/dominx
Project-URL: Tracker, https://github.com/zenthm/dominx/issues
Keywords: python,gamedev,game-engine,python-library,game-development,game-framework,game-library,game-dev
Classifier: Development Status :: 3 - Alpha
Classifier: Environment :: MacOS X :: Cocoa
Classifier: Environment :: Win32 (MS Windows)
Classifier: Environment :: X11 Applications
Classifier: Intended Audience :: Developers
Classifier: License :: OSI Approved :: MIT License
Classifier: Operating System :: MacOS :: MacOS X
Classifier: Operating System :: Microsoft :: Windows
Classifier: Operating System :: POSIX
Classifier: Programming Language :: Python :: 3
Classifier: Programming Language :: Python :: 3 :: Only
Classifier: Programming Language :: Python :: 3.7
Classifier: Programming Language :: Python :: 3.8
Classifier: Programming Language :: Python :: 3.9
Classifier: Programming Language :: Python :: 3.10
Classifier: Programming Language :: Python :: 3.11
Classifier: Programming Language :: Python :: Implementation :: CPython
Classifier: Topic :: Games/Entertainment
Requires-Python: >=3.7
License-File: LICENSE.txt
